<?xml version="1.0" encoding="UTF-8" standalone="yes" ?>
<?xml-stylesheet type="text/xsl" href="../web/bra.xslt"?>
<BULLETINS_NEIGE_AVALANCHE xmlns:xsi="http://www.w3.org/2001/XMLSchema-instance" xmlns:xsd="http://www.w3.org/2001/XMLSchema" TYPEBULLETIN="BRA" ID="4" MASSIF="Bauges" DATEBULLETIN="2024-04-07T15:00:00" DATEECHEANCE="2024-04-08T18:00:00" DATEVALIDITE="2024-04-08T18:00:00" DATEDIFFUSION="2024-04-07T15:13:27" AMENDEMENT="false">
  <DateValidite>2024-04-08T18:00:00</DateValidite>
  <CARTOUCHERISQUE>
    <RISQUE RISQUE1="1" EVOLURISQUE1="" LOC1="" ALTITUDE="" RISQUE2="" EVOLURISQUE2="" LOC2="" RISQUEMAXI="1" COMMENTAIRE="Risque faible." RISQUEMAXIJ2="2" DATE_RISQUE_J2="2024-04-09T00:00:00"/>
    <PENTE NE="false" E="false" SE="false" S="false" SW="false" W="false" NW="false" N="false" COMMENTAIRE=""/>
    <ACCIDENTEL>uniquement en neige humide.</ACCIDENTEL>
    <NATUREL>plaques de fond.</NATUREL>
    <RESUME>Départs spontanés : plaques de fond.
Déclenchements skieurs : uniquement en neige humide.</RESUME>
    <RisqueJ2>risque limité</RisqueJ2>
    <CommentaireRisqueJ2>Les températures chutent et la neige fait son retour dès 1000m, significatives à partir de 1400m.</CommentaireRisqueJ2>
    <AVIS/>
    <VIGILANCE/>
    <ImageRisque>montagne_risques_4.png</ImageRisque>
    <ImagePente>rose_pentes_4.png</ImagePente>
  </CARTOUCHERISQUE>
  <STABILITE>
    <SitAvalTyp SAT1="4" SAT2=""/>
    <TEXTE>Douceur remarquable pour la saison, risque de plaques de fond.

DEPARTS SPONTANES : Sans regel et avec températures élevées de rares ( car la plus part sont déjà parties) avalanches de fond peuvent se produire.


DECLENCHEMENTS PROVOQUES : En tous secteurs, un skieur peut favoriser un départ en neige humide dans les pentes raides.</TEXTE>
  </STABILITE>
  <QUALITE>
    <TEXTE>Manteau neigeux de fin de saison, seules quelques combes Nord restent réellement skiables sans rayer les skis. 
Limites skiables : au-dessus de 1700/1900 m, hors secteurs sud dégarnis.
Qualité de la neige : neige de printemps sans regel.</TEXTE>
  </QUALITE>
  <ENNEIGEMENT DATE="2024-04-07T06:00:00" LimiteSud="2200" LimiteNord="1700">
    <NIVEAU ALTI="1000" N="0" S="0"/>
    <NIVEAU ALTI="1500" N="0" S="0"/>
    <NIVEAU ALTI="2000" N="40" S="0"/>
    <ImageEnneigement>montagne_enneigement_4.png</ImageEnneigement>
  </ENNEIGEMENT>
  <NEIGEFRAICHE ALTITUDESS="1800">
    <NEIGE24H DATE="2024-04-03T00:00:00" SS24Min="1" SS24Max="2"/>
    <NEIGE24H DATE="2024-04-04T00:00:00" SS24Min="0" SS24Max="0"/>
    <NEIGE24H DATE="2024-04-05T00:00:00" SS24Min="0" SS24Max="0"/>
    <NEIGE24H DATE="2024-04-06T00:00:00" SS24Min="0" SS24Max="0"/>
    <NEIGE24H DATE="2024-04-07T00:00:00" SS24Min="0" SS24Max="0"/>
    <NEIGE24H DATE="2024-04-08T00:00:00" SS24Min="0" SS24Max="0"/>
    <ImageNeigeFraiche>graphe_neige_fraiche_4.png</ImageNeigeFraiche>
  </NEIGEFRAICHE>
  <METEO ALTITUDEVENT1="1500" ALTITUDEVENT2="2000">
    <COMMENTAIRE>Voilé à couvert avec une luminosité ternie par du sable en suspension. Isotherme 0°C vers 3600m, vent de sud assez fort en altitude</COMMENTAIRE>
    <ECHEANCE DATE="2024-04-08T06:00:00" FF1="25" DD1="S" FF2="40" DD2="S" ISO0="3700" PLUIENEIGE="-1" TEMPSSENSIBLE="4" MERNUAGES="-1"/>
    <ECHEANCE DATE="2024-04-08T12:00:00" FF1="25" DD1="S" FF2="35" DD2="S" ISO0="3600" PLUIENEIGE="-1" TEMPSSENSIBLE="4" MERNUAGES="-1"/>
    <ECHEANCE DATE="2024-04-08T18:00:00" FF1="40" DD1="S" FF2="55" DD2="SE" ISO0="3500" PLUIENEIGE="-1" TEMPSSENSIBLE="4" MERNUAGES="-1"/>
    <ECHEANCE DATE="2024-04-09T00:00:00" FF1="25" DD1="S" FF2="35" DD2="S" ISO0="3400" PLUIENEIGE="-1" TEMPSSENSIBLE="4" MERNUAGES="-1"/>
    <ImageMeteo>apercu_meteo_4.png</ImageMeteo>
  </METEO>
  <BSH>
    <METEO>
      <ECHEANCE DATE="2024-04-01T06:00:00" FF1="50" DD1="O" FF2="60" DD2="O" ISO0="1400" PLUIENEIGE="1100" TEMPSSENSIBLE="63"/>
      <ECHEANCE DATE="2024-04-01T12:00:00" FF1="20" DD1="O" FF2="30" DD2="O" ISO0="1500" PLUIENEIGE="1200" TEMPSSENSIBLE="80"/>
      <ECHEANCE DATE="2024-04-01T18:00:00" FF1="30" DD1="O" FF2="40" DD2="O" ISO0="1700" PLUIENEIGE="1300" TEMPSSENSIBLE="80"/>
      <ECHEANCE DATE="2024-04-02T00:00:00" FF1="30" DD1="O" FF2="40" DD2="O" ISO0="1500" PLUIENEIGE="1200" TEMPSSENSIBLE="61"/>
      <ECHEANCE DATE="2024-04-02T06:00:00" FF1="20" DD1="O" FF2="30" DD2="O" ISO0="1500" PLUIENEIGE="-1" TEMPSSENSIBLE="61"/>
      <ECHEANCE DATE="2024-04-02T12:00:00" FF1="10" DD1="SO" FF2="20" DD2="SO" ISO0="1500" PLUIENEIGE="-1" TEMPSSENSIBLE="80"/>
      <ECHEANCE DATE="2024-04-02T18:00:00" FF1="25" DD1="SO" FF2="30" DD2="SO" ISO0="2000" PLUIENEIGE="-1" TEMPSSENSIBLE="3"/>
      <ECHEANCE DATE="2024-04-03T00:00:00" FF1="35" DD1="SO" FF2="45" DD2="SO" ISO0="2300" PLUIENEIGE="-1" TEMPSSENSIBLE="6"/>
      <ECHEANCE DATE="2024-04-03T06:00:00" FF1="10" DD1="S" FF2="25" DD2="SO" ISO0="2000" PLUIENEIGE="1500" TEMPSSENSIBLE="61"/>
      <ECHEANCE DATE="2024-04-03T12:00:00" FF1="30" DD1="SO" FF2="35" DD2="O" ISO0="1800" PLUIENEIGE="1500" TEMPSSENSIBLE="80"/>
      <ECHEANCE DATE="2024-04-03T18:00:00" FF1="20" DD1="SO" FF2="25" DD2="O" ISO0="2200" PLUIENEIGE="1800" TEMPSSENSIBLE="71"/>
      <ECHEANCE DATE="2024-04-04T00:00:00" FF1="35" DD1="O" FF2="45" DD2="O" ISO0="2200" PLUIENEIGE="-1" TEMPSSENSIBLE="2"/>
      <ECHEANCE DATE="2024-04-04T06:00:00" FF1="35" DD1="O" FF2="45" DD2="NO" ISO0="2200" PLUIENEIGE="-1" TEMPSSENSIBLE="6"/>
      <ECHEANCE DATE="2024-04-04T12:00:00" FF1="35" DD1="SO" FF2="50" DD2="SO" ISO0="2500" PLUIENEIGE="-1" TEMPSSENSIBLE="4"/>
      <ECHEANCE DATE="2024-04-04T18:00:00" FF1="15" DD1="SO" FF2="40" DD2="SO" ISO0="2600" PLUIENEIGE="-1" TEMPSSENSIBLE="4"/>
      <ECHEANCE DATE="2024-04-05T00:00:00" FF1="10" DD1="SO" FF2="20" DD2="SO" ISO0="2700" PLUIENEIGE="-1" TEMPSSENSIBLE="4"/>
      <ECHEANCE DATE="2024-04-05T06:00:00" FF1="15" DD1="SO" FF2="20" DD2="SO" ISO0="2800" PLUIENEIGE="-1" TEMPSSENSIBLE="6"/>
      <ECHEANCE DATE="2024-04-05T12:00:00" FF1="35" DD1="SO" FF2="50" DD2="SO" ISO0="3300" PLUIENEIGE="-1" TEMPSSENSIBLE="6"/>
      <ECHEANCE DATE="2024-04-05T18:00:00" FF1="15" DD1="S" FF2="25" DD2="SO" ISO0="3500" PLUIENEIGE="-1" TEMPSSENSIBLE="6"/>
      <ECHEANCE DATE="2024-04-06T00:00:00" FF1="20" DD1="SO" FF2="30" DD2="SO" ISO0="3700" PLUIENEIGE="-1" TEMPSSENSIBLE="6"/>
      <ECHEANCE DATE="2024-04-06T06:00:00" FF1="20" DD1="S" FF2="30" DD2="SO" ISO0="3600" PLUIENEIGE="-1" TEMPSSENSIBLE="6"/>
      <ECHEANCE DATE="2024-04-06T12:00:00" FF1="20" DD1="S" FF2="35" DD2="S" ISO0="4000" PLUIENEIGE="-1" TEMPSSENSIBLE="6"/>
      <ECHEANCE DATE="2024-04-06T18:00:00" FF1="25" DD1="S" FF2="40" DD2="SO" ISO0="4000" PLUIENEIGE="-1" TEMPSSENSIBLE="1"/>
      <ECHEANCE DATE="2024-04-07T00:00:00" FF1="30" DD1="S" FF2="55" DD2="SO" ISO0="3900" PLUIENEIGE="-1" TEMPSSENSIBLE="6"/>
      <ECHEANCE DATE="2024-04-07T06:00:00" FF1="40" DD1="S" FF2="50" DD2="SO" ISO0="3900" PLUIENEIGE="-1" TEMPSSENSIBLE="6"/>
      <ECHEANCE DATE="2024-04-07T12:00:00" FF1="35" DD1="S" FF2="55" DD2="SO" ISO0="3700" PLUIENEIGE="-1" TEMPSSENSIBLE="4"/>
      <ECHEANCE DATE="2024-04-07T18:00:00" FF1="50" DD1="S" FF2="65" DD2="S" ISO0="3700" PLUIENEIGE="-1" TEMPSSENSIBLE="4"/>
      <ECHEANCE DATE="2024-04-08T00:00:00" FF1="40" DD1="S" FF2="55" DD2="S" ISO0="3700" PLUIENEIGE="-1" TEMPSSENSIBLE="4"/>
    </METEO>
    <ENNEIGEMENTS>
      <ENNEIGEMENT DATE="2024-04-01T00:00:00" LimiteSud="1500" LimiteNord="1500">
        <NIVEAU ALTI="1000" N="0" S="0"/>
        <NIVEAU ALTI="1500" N="2" S="2"/>
        <NIVEAU ALTI="2000" N="60" S="10"/>
      </ENNEIGEMENT>
      <ENNEIGEMENT DATE="2024-04-02T00:00:00" LimiteSud="1400" LimiteNord="1400">
        <NIVEAU ALTI="1000" N="0" S="0"/>
        <NIVEAU ALTI="1500" N="10" S="10"/>
        <NIVEAU ALTI="2000" N="70" S="20"/>
      </ENNEIGEMENT>
      <ENNEIGEMENT DATE="2024-04-03T00:00:00" LimiteSud="1400" LimiteNord="1400">
        <NIVEAU ALTI="1000" N="0" S="0"/>
        <NIVEAU ALTI="1500" N="10" S="10"/>
        <NIVEAU ALTI="2000" N="70" S="20"/>
      </ENNEIGEMENT>
      <ENNEIGEMENT DATE="2024-04-04T00:00:00" LimiteSud="2000" LimiteNord="1600">
        <NIVEAU ALTI="1000" N="0" S="0"/>
        <NIVEAU ALTI="1500" N="0" S="0"/>
        <NIVEAU ALTI="2000" N="70" S="20"/>
      </ENNEIGEMENT>
      <ENNEIGEMENT DATE="2024-04-05T00:00:00" LimiteSud="2000" LimiteNord="1700">
        <NIVEAU ALTI="1000" N="0" S="0"/>
        <NIVEAU ALTI="1500" N="0" S="0"/>
        <NIVEAU ALTI="2000" N="50" S="5"/>
      </ENNEIGEMENT>
      <ENNEIGEMENT DATE="2024-04-06T00:00:00" LimiteSud="2200" LimiteNord="1700">
        <NIVEAU ALTI="1000" N="0" S="0"/>
        <NIVEAU ALTI="1500" N="0" S="0"/>
        <NIVEAU ALTI="2000" N="45" S="0"/>
      </ENNEIGEMENT>
      <ENNEIGEMENT DATE="2024-04-07T06:00:00" LimiteSud="2200" LimiteNord="1700">
        <NIVEAU ALTI="1000" N="0" S="0"/>
        <NIVEAU ALTI="1500" N="0" S="0"/>
        <NIVEAU ALTI="2000" N="40" S="0"/>
      </ENNEIGEMENT>
    </ENNEIGEMENTS>
    <NEIGEFRAICHE ALTITUDESS="1800">
      <NEIGE24H DATE="2024-04-02T00:00:00" SS24Min="5" SS24Max="10"/>
      <NEIGE24H DATE="2024-04-03T00:00:00" SS24Min="1" SS24Max="5"/>
      <NEIGE24H DATE="2024-04-04T00:00:00" SS24Min="1" SS24Max="2"/>
      <NEIGE24H DATE="2024-04-05T00:00:00" SS24Min="0" SS24Max="0"/>
      <NEIGE24H DATE="2024-04-06T00:00:00" SS24Min="0" SS24Max="0"/>
      <NEIGE24H DATE="2024-04-07T06:00:00" SS24Min="0" SS24Max="0"/>
    </NEIGEFRAICHE>
    <RISQUES>
      <RISQUE DATE="2024-04-01T00:00:00" RISQUEMAXI="2"/>
      <RISQUE DATE="2024-04-02T00:00:00" RISQUEMAXI="2"/>
      <RISQUE DATE="2024-04-03T00:00:00" RISQUEMAXI="2"/>
      <RISQUE DATE="2024-04-04T00:00:00" RISQUEMAXI="2"/>
      <RISQUE DATE="2024-04-05T00:00:00" RISQUEMAXI="2"/>
      <RISQUE DATE="2024-04-06T00:00:00" RISQUEMAXI="2"/>
      <RISQUE DATE="2024-04-07T00:00:00" RISQUEMAXI="1"/>
    </RISQUES>
    <Image7derniersjours>sept_derniers_jours_4.png</Image7derniersjours>
    <Image7derniersjours_portrait>sept_derniers_jours_portrait_4.png</Image7derniersjours_portrait>
  </BSH>
  <TexteMeta>
    <Vigilance>Pour consulter la vigilance en cours, veuillez vous rendre sur le site <a href="https://vigilance.meteofrance.fr/fr">https://vigilance.meteofrance.fr/fr</a></Vigilance>
    <EnteteGenerique/>
    <BasDePageGenerique/>
    <LienDocumentation/>
    <Partenaires>Rédigé par Météo-France avec la contribution des observateurs du réseau nivo-météorologique. Partenariat : ANMSM (Maires de Stations de Montagne), DSF (Domaines Skiables de France), ADSP (Directeurs de Pistes et de la Sécurité des Stations de Sports d'Hiver) et autres acteurs de la montagne.</Partenaires>
  </TexteMeta>
</BULLETINS_NEIGE_AVALANCHE>