{
  "bulletins" : [ {
    "publicationTime" : "2026-02-16T16:00:00Z",
    "validTime" : {
      "startTime" : "2026-02-16T23:00:00Z",
      "endTime" : "2026-02-17T23:00:00Z"
    },
    "unscheduled" : false,
    "weatherForecast" : { },
    "avalancheActivity" : {
      "highlights" : "Weiterer Anstieg der Gefahr von trockenen Lawinen mit Neuschnee und starkem Wind.",
      "comment" : "Mit Schneefall oberhalb von rund 1000 m und teils stürmischem Nordwestwind wachsen die Triebschneeansammlungen im Tagesverlauf an. Nach Südosten hin nehmen Anzahl und Größe der Gefahrenstellen zu. <br/> Besonders an sehr steilen Hängen und an Triebschneehängen sind zahlreiche mittlere und mehrfach große spontane Lawinen zu erwarten. Die Lawinen können dort in tiefen Schichten ausgelöst werden und sehr groß werden. <br/> Die Lawinen können vor allem in den typischen Lawinenzügen bis in Tallagen vorstoßen und exponierte Verkehrswege gefährden. <br/> Für Touren und Variantenabfahrten abseits gesicherter Pisten sind die Verhältnisse sehr heikel. <br/> Fernauslösungen sind möglich. Einzelne Wintersportler können Lawinen auslösen, auch große. Vorsicht an steilen Hängen und in Rinnen, Mulden und hinter Geländekanten."
    },
    "snowpackStructure" : {
      "comment" : "Bis in die Nacht fallen oberhalb von rund 1500 m verbreitet 40 bis 60 cm Schnee, lokal bis zu 80 cm. Bis Dienstag fallen oberhalb von rund 1000 m verbreitet 10 bis 25 cm Schnee. Am Montag blies der Wind verbreitet stark bis stürmisch. Bis Dienstag bläst der Wind verbreitet stark bis stürmisch. <br/> Der Neuschnee sowie die während dem Schneefall entstehenden Triebschneeansammlungen werden zunehmend störanfällig. <br/> Die Schneedecke ist ungünstig geschichtet. <br/> In Kamm- und Passlagen liegen je nach Windeinfluss sehr unterschiedliche Schneehöhen. <br/> Im Tagesverlauf sind mehrere mittlere bis große spontane trockene Lawinen abgegangen. In den letzten Tagen wurden mehrere Schneebrettlawinen ausgelöst."
    },
    "travelAdvisory" : { },
    "tendency" : [ {
      "highlights" : "Die Wetterbedingungen erlauben eine allmähliche Verfestigung der Schneedecke.",
      "tendencyType" : "decreasing",
      "validTime" : {
        "startTime" : "2026-02-17T23:00:00Z",
        "endTime" : "2026-02-18T23:00:00Z"
      }
    } ],
    "customData" : {
      "ALBINA" : {
        "mainDate" : "2026-02-17"
      },
      "LWD_Tyrol" : {
        "dangerPatterns" : [ "DP6", "DP1" ]
      }
    },
    "avalancheProblems" : [ {
      "problemType" : "wind_slab",
      "elevation" : {
        "lowerBound" : "1800"
      },
      "validTimePeriod" : "all_day",
      "snowpackStability" : "very_poor",
      "frequency" : "some",
      "avalancheSize" : 4,
      "aspects" : [ "SE", "W", "SW", "E", "NW", "NE", "N", "S" ]
    }, {
      "problemType" : "new_snow",
      "elevation" : { },
      "validTimePeriod" : "all_day",
      "snowpackStability" : "very_poor",
      "frequency" : "many",
      "avalancheSize" : 3,
      "aspects" : [ "SE", "W", "SW", "E", "NW", "NE", "N", "S" ]
    } ],
    "bulletinID" : "1215b5b9-c679-4d2d-be97-143ca587c9fe",
    "dangerRatings" : [ {
      "mainValue" : "high",
      "validTimePeriod" : "all_day"
    } ],
    "lang" : "de",
    "regions" : [ {
      "name" : "D - CERVINIA E ALTA VALPELLINE",
      "regionID" : "IT-23-AO-20"
    }, {
      "name" : "A - TESTATA SAINT-BARTHELEMY",
      "regionID" : "IT-23-AO-23"
    }, {
      "name" : "A - SAINT-PIERRE SAINT-NICHOLAS",
      "regionID" : "IT-23-AO-01"
    }, {
      "name" : "A - VALTOURNENCHE",
      "regionID" : "IT-23-AO-24"
    }, {
      "name" : "C - VALSAVARENCHE",
      "regionID" : "IT-23-AO-13"
    }, {
      "name" : "C - VAL DI RHEMES",
      "regionID" : "IT-23-AO-21"
    }, {
      "name" : "D - VAL VENY",
      "regionID" : "IT-23-AO-22"
    }, {
      "name" : "D - VALGRISENCHE",
      "regionID" : "IT-23-AO-16"
    }, {
      "name" : "D - LA SALLE MORGEX",
      "regionID" : "IT-23-AO-17"
    }, {
      "name" : "B - ALTA VALLE DI GRESSONEY",
      "regionID" : "IT-23-AO-06"
    }, {
      "name" : "B - TESTATA VAL D'AYAS SAINT-JACQUES",
      "regionID" : "IT-23-AO-25"
    }, {
      "name" : "D - VAL FERRET",
      "regionID" : "IT-23-AO-14"
    }, {
      "name" : "D - VALLE DI LA THUILE",
      "regionID" : "IT-23-AO-15"
    }, {
      "name" : "D - GRAN SAN BERNARDO OLLOMONT",
      "regionID" : "IT-23-AO-18"
    }, {
      "name" : "D - BASSA E MEDIA VALPELLINE",
      "regionID" : "IT-23-AO-19"
    } ]
  }, {
    "publicationTime" : "2026-02-16T16:00:00Z",
    "validTime" : {
      "startTime" : "2026-02-16T23:00:00Z",
      "endTime" : "2026-02-17T23:00:00Z"
    },
    "unscheduled" : false,
    "weatherForecast" : { },
    "avalancheActivity" : {
      "highlights" : "Allmählicher Anstieg der Gefahr von trockenen Lawinen mit Neuschnee und starkem Wind.",
      "comment" : "Mit Neuschnee und starkem Wind nehmen Anzahl und Größe der Gefahrenstellen zu. <br/> Hoch gelegene Einzugsgebiete werden mit Schneefall und Wind weiter aufgefüllt. <br/> Besonders an sehr steilen Hängen und an Triebschneehängen sind mittlere spontane Lawinen möglich. <br/> Die Lawinen können stellenweise im Altschnee ausgelöst werden und recht groß werden. <br/> Fernauslösungen sind möglich. Schwachschichten im Altschnee erfordern Vorsicht. Wummgeräusche und Risse beim Betreten der Schneedecke sind Alarmzeichen. <br/> Einzelne Wintersportler können Lawinen auslösen. Vorsicht an steilen Hängen und in Rinnen, Mulden und hinter Geländekanten. <br/>"
    },
    "snowpackStructure" : {
      "comment" : "Bis in die Nacht fallen oberhalb von rund 1600 m verbreitet 15 bis 40 cm Schnee. Bis Dienstag fallen oberhalb von rund 1200 m verbreitet 10 bis 20 cm Schnee. Der Wind bläst stark bis stürmisch. <br/> In Kamm- und Passlagen liegen je nach Windeinfluss sehr unterschiedliche Schneehöhen. Die Schneedecke ist ungünstig geschichtet. <br/> In der Altschneedecke sind v.a. an West-, Nord- und Osthängen kantig aufgebaute Schwachschichten vorhanden. <br/>"
    },
    "travelAdvisory" : { },
    "tendency" : [ {
      "highlights" : "Die Wetterbedingungen erlauben eine langsame Verfestigung der Schneedecke.",
      "tendencyType" : "steady",
      "validTime" : {
        "startTime" : "2026-02-17T23:00:00Z",
        "endTime" : "2026-02-18T23:00:00Z"
      }
    } ],
    "customData" : {
      "ALBINA" : {
        "mainDate" : "2026-02-17"
      },
      "LWD_Tyrol" : {
        "dangerPatterns" : [ "DP6", "DP1" ]
      }
    },
    "avalancheProblems" : [ {
      "problemType" : "wind_slab",
      "elevation" : {
        "lowerBound" : "1800"
      },
      "validTimePeriod" : "all_day",
      "snowpackStability" : "very_poor",
      "frequency" : "some",
      "avalancheSize" : 3,
      "aspects" : [ "SE", "W", "SW", "E", "NW", "NE", "N", "S" ]
    }, {
      "problemType" : "new_snow",
      "elevation" : { },
      "validTimePeriod" : "all_day",
      "snowpackStability" : "poor",
      "frequency" : "many",
      "avalancheSize" : 2,
      "aspects" : [ "SE", "W", "SW", "E", "NW", "NE", "N", "S" ]
    } ],
    "bulletinID" : "de4b268b-f204-4119-8c8d-f01d61adfd45",
    "dangerRatings" : [ {
      "mainValue" : "considerable",
      "validTimePeriod" : "all_day"
    } ],
    "lang" : "de",
    "regions" : [ {
      "name" : "C - VAL DI COGNE AYMAVILLES",
      "regionID" : "IT-23-AO-12"
    }, {
      "name" : "A - INTROD ARVIER",
      "regionID" : "IT-23-AO-02"
    }, {
      "name" : "B - CHAMPDEPRAZ MONTE AVIC",
      "regionID" : "IT-23-AO-10"
    }, {
      "name" : "B - VALLE DI CHAMPORCHER",
      "regionID" : "IT-23-AO-11"
    }, {
      "name" : "A - BASSA VALTOURNENCHE CHATILLON",
      "regionID" : "IT-23-AO-05"
    }, {
      "name" : "A - QUART NUS",
      "regionID" : "IT-23-AO-03"
    }, {
      "name" : "A - PONTEY",
      "regionID" : "IT-23-AO-26"
    }, {
      "name" : "A - POLLEIN SAINT MARCEL",
      "regionID" : "IT-23-AO-04"
    }, {
      "name" : "B - VALLI DI GRESSONEY, AYAS, CHAMPORCHER",
      "regionID" : "IT-23-AO-09"
    }, {
      "name" : "B - MEDIA VAL D'AYAS BRUSSON",
      "regionID" : "IT-23-AO-07"
    }, {
      "name" : "B - MEDIA VALLE DEL LYS",
      "regionID" : "IT-23-AO-08"
    } ]
  } ]
}