<?xml version="1.0" encoding="UTF-8" standalone="no"?>
<ObsCollection xmlns="http://caaml.org/Schemas/V5.0/Profiles/BulletinEAWS" xmlns:gml="http://www.opengis.net/gml" xmlns:xlink="http://www.w3.org/1999/xlink" xmlns:xsi="http://www.w3.org/2001/XMLSchema-instance" xml:lang="en" xsi:schemaLocation="http://caaml.org/Schemas/V5.0/Profiles/BulletinEAWS http://caaml.org/Schemas/V5.0/Profiles/BulletinEAWS/CAAMLv5_BulletinEAWS.xsd">
  <metaDataProperty>
    <MetaData>
      <dateTimeReport>2025-02-20T16:00:00Z</dateTimeReport>
      <srcRef>
        <Operation>
          <name>Avalanche.report</name>
        </Operation>
      </srcRef>
    </MetaData>
  </metaDataProperty>
  <observations>
    <Bulletin gml:id="623ff199-3273-4e67-990b-c48179457f2a" xml:lang="en">
      <metaDataProperty>
        <MetaData>
          <dateTimeReport>2025-02-20T16:00:00Z</dateTimeReport>
          <srcRef>
            <Operation>
              <name>Avalanche.report</name>
            </Operation>
          </srcRef>
        </MetaData>
      </metaDataProperty>
      <validTime>
        <TimePeriod>
          <beginPosition>2025-02-20T23:00:00Z</beginPosition>
          <endPosition>2025-02-21T11:00:00Z</endPosition>
        </TimePeriod>
      </validTime>
      <srcRef>
        <Operation>
          <name>Avalanche.report</name>
        </Operation>
      </srcRef>
      <locRef xlink:href="IT-23-AO-12"/>
      <locRef xlink:href="IT-23-AO-13"/>
      <locRef xlink:href="IT-23-AO-10"/>
      <locRef xlink:href="IT-23-AO-11"/>
      <locRef xlink:href="IT-23-AO-16"/>
      <locRef xlink:href="IT-23-AO-17"/>
      <locRef xlink:href="IT-23-AO-14"/>
      <locRef xlink:href="IT-23-AO-15"/>
      <locRef xlink:href="IT-23-AO-18"/>
      <locRef xlink:href="IT-23-AO-19"/>
      <locRef xlink:href="IT-23-AO-20"/>
      <locRef xlink:href="IT-23-AO-23"/>
      <locRef xlink:href="IT-23-AO-01"/>
      <locRef xlink:href="IT-23-AO-24"/>
      <locRef xlink:href="IT-23-AO-02"/>
      <locRef xlink:href="IT-23-AO-21"/>
      <locRef xlink:href="IT-23-AO-22"/>
      <locRef xlink:href="IT-23-AO-05"/>
      <locRef xlink:href="IT-23-AO-06"/>
      <locRef xlink:href="IT-23-AO-25"/>
      <locRef xlink:href="IT-23-AO-03"/>
      <locRef xlink:href="IT-23-AO-26"/>
      <locRef xlink:href="IT-23-AO-04"/>
      <locRef xlink:href="IT-23-AO-09"/>
      <locRef xlink:href="IT-23-AO-07"/>
      <locRef xlink:href="IT-23-AO-08"/>
      <bulletinResultsOf>
        <BulletinMeasurements>
          <dangerRatings>
            <DangerRating>
              <mainValue>2</mainValue>
            </DangerRating>
          </dangerRatings>
          <avProblems>
            <AvProblem>
              <type>wet snow</type>
              <validAspect xlink:href="AspectRange_w"/>
              <validAspect xlink:href="AspectRange_s"/>
              <validAspect xlink:href="AspectRange_sw"/>
              <validAspect xlink:href="AspectRange_se"/>
              <validElevation>
                <elevationRange uom="m">
                  <beginPosition>1900</beginPosition>
                  <endPosition>2700</endPosition>
                </elevationRange>
              </validElevation>
            </AvProblem>
          </avProblems>
          <tendency>
            <type>steady</type>
            <validTime>
              <TimePeriod>
                <beginPosition>2025-02-21T23:00:00Z</beginPosition>
                <endPosition>2025-02-22T23:00:00Z</endPosition>
              </TimePeriod>
            </validTime>
          </tendency>
          <avActivityHighlights>Field observations and stability tests have shown a favourable avalanche situation.</avActivityHighlights>
          <avActivityComment>Where night cloudy cover will be most persistent: The surface of the snowpack will cool hardly at all during the overcast night and will already be soft in the early morning. Until the temperature falls small and, in isolated cases, medium-sized moist and wet avalanches are possible. &lt;br/&gt; &lt;br/&gt; Backcountry tourers or freeriders can release avalanches in some places, with a large load in most cases. They are rather small. Such avalanche prone locations are to be found on extremely steep southeast, south and southwest facing slopes. Apart from the danger of being buried, restraint should be exercised in particular in view of the danger of avalanches sweeping people along and giving rise to falls. In steep terrain there is a danger of falling on the hard snow surface. &lt;br/&gt; Gradual decrease in danger as the temperature drops.</avActivityComment>
          <snowpackStructureComment>Thursday: In the afternoon on extremely steep south facing slopes individual mostly small avalanches were released. &lt;br/&gt; As a consequence of highly fluctuating temperatures a crust formed on the surface during the last few days, in particular on sunny slopes below approximately 2800 m. In some localities a partly overcast night: The surface of the snowpack is hardly frozen at all. This applies already during the night. &lt;br/&gt; In shady places that are protected from the wind intermediate and high altitudes: Towards its surface, the snowpack is dry and has a loosely bonded surface. &lt;br/&gt; Snow depths vary greatly above approximately 2200 m, depending on the infuence of the wind. Adjacent to ridgelines and in pass areas and at high altitude a little snow is lying. At low altitude less snow than usual is lying. In the south-east of the region, watch out for the numerous rocks hidden by the little recent snow. &lt;br/&gt; &lt;br/&gt; Towards its base, the snowpack consists of faceted crystals. This applies in particular on steep east, north and northwest facing slopes,.</snowpackStructureComment>
          <tendencyComment>The avalanche danger will persist.</tendencyComment>
        </BulletinMeasurements>
      </bulletinResultsOf>
    </Bulletin>
    <Bulletin gml:id="623ff199-3273-4e67-990b-c48179457f2a_PM" xml:lang="en">
      <metaDataProperty>
        <MetaData>
          <dateTimeReport>2025-02-20T16:00:00Z</dateTimeReport>
          <srcRef>
            <Operation>
              <name>Avalanche.report</name>
            </Operation>
          </srcRef>
        </MetaData>
      </metaDataProperty>
      <validTime>
        <TimePeriod>
          <beginPosition>2025-02-21T11:00:00Z</beginPosition>
          <endPosition>2025-02-21T23:00:00Z</endPosition>
        </TimePeriod>
      </validTime>
      <srcRef>
        <Operation>
          <name>Avalanche.report</name>
        </Operation>
      </srcRef>
      <locRef xlink:href="IT-23-AO-12"/>
      <locRef xlink:href="IT-23-AO-13"/>
      <locRef xlink:href="IT-23-AO-10"/>
      <locRef xlink:href="IT-23-AO-11"/>
      <locRef xlink:href="IT-23-AO-16"/>
      <locRef xlink:href="IT-23-AO-17"/>
      <locRef xlink:href="IT-23-AO-14"/>
      <locRef xlink:href="IT-23-AO-15"/>
      <locRef xlink:href="IT-23-AO-18"/>
      <locRef xlink:href="IT-23-AO-19"/>
      <locRef xlink:href="IT-23-AO-20"/>
      <locRef xlink:href="IT-23-AO-23"/>
      <locRef xlink:href="IT-23-AO-01"/>
      <locRef xlink:href="IT-23-AO-24"/>
      <locRef xlink:href="IT-23-AO-02"/>
      <locRef xlink:href="IT-23-AO-21"/>
      <locRef xlink:href="IT-23-AO-22"/>
      <locRef xlink:href="IT-23-AO-05"/>
      <locRef xlink:href="IT-23-AO-06"/>
      <locRef xlink:href="IT-23-AO-25"/>
      <locRef xlink:href="IT-23-AO-03"/>
      <locRef xlink:href="IT-23-AO-26"/>
      <locRef xlink:href="IT-23-AO-04"/>
      <locRef xlink:href="IT-23-AO-09"/>
      <locRef xlink:href="IT-23-AO-07"/>
      <locRef xlink:href="IT-23-AO-08"/>
      <bulletinResultsOf>
        <BulletinMeasurements>
          <dangerRatings>
            <DangerRating>
              <mainValue>1</mainValue>
            </DangerRating>
          </dangerRatings>
          <avProblems>
            <AvProblem>
              <type>wet snow</type>
              <validAspect xlink:href="AspectRange_w"/>
              <validAspect xlink:href="AspectRange_s"/>
              <validAspect xlink:href="AspectRange_sw"/>
              <validAspect xlink:href="AspectRange_se"/>
              <validElevation>
                <elevationRange uom="m">
                  <beginPosition>1900</beginPosition>
                  <endPosition>2700</endPosition>
                </elevationRange>
              </validElevation>
            </AvProblem>
          </avProblems>
          <tendency>
            <type>steady</type>
            <validTime>
              <TimePeriod>
                <beginPosition>2025-02-21T23:00:00Z</beginPosition>
                <endPosition>2025-02-22T23:00:00Z</endPosition>
              </TimePeriod>
            </validTime>
          </tendency>
          <avActivityHighlights>Field observations and stability tests have shown a favourable avalanche situation.</avActivityHighlights>
          <avActivityComment>Where night cloudy cover will be most persistent: The surface of the snowpack will cool hardly at all during the overcast night and will already be soft in the early morning. Until the temperature falls small and, in isolated cases, medium-sized moist and wet avalanches are possible. &lt;br/&gt; &lt;br/&gt; Backcountry tourers or freeriders can release avalanches in some places, with a large load in most cases. They are rather small. Such avalanche prone locations are to be found on extremely steep southeast, south and southwest facing slopes. Apart from the danger of being buried, restraint should be exercised in particular in view of the danger of avalanches sweeping people along and giving rise to falls. In steep terrain there is a danger of falling on the hard snow surface. &lt;br/&gt; Gradual decrease in danger as the temperature drops.</avActivityComment>
          <snowpackStructureComment>Thursday: In the afternoon on extremely steep south facing slopes individual mostly small avalanches were released. &lt;br/&gt; As a consequence of highly fluctuating temperatures a crust formed on the surface during the last few days, in particular on sunny slopes below approximately 2800 m. In some localities a partly overcast night: The surface of the snowpack is hardly frozen at all. This applies already during the night. &lt;br/&gt; In shady places that are protected from the wind intermediate and high altitudes: Towards its surface, the snowpack is dry and has a loosely bonded surface. &lt;br/&gt; Snow depths vary greatly above approximately 2200 m, depending on the infuence of the wind. Adjacent to ridgelines and in pass areas and at high altitude a little snow is lying. At low altitude less snow than usual is lying. In the south-east of the region, watch out for the numerous rocks hidden by the little recent snow. &lt;br/&gt; &lt;br/&gt; Towards its base, the snowpack consists of faceted crystals. This applies in particular on steep east, north and northwest facing slopes,.</snowpackStructureComment>
          <tendencyComment>The avalanche danger will persist.</tendencyComment>
        </BulletinMeasurements>
      </bulletinResultsOf>
    </Bulletin>
  </observations>
</ObsCollection>
