<?xml version="1.0" encoding="UTF-8" standalone="no"?>
<ObsCollection xmlns="http://caaml.org/Schemas/V5.0/Profiles/BulletinEAWS" xmlns:gml="http://www.opengis.net/gml" xmlns:xlink="http://www.w3.org/1999/xlink" xmlns:xsi="http://www.w3.org/2001/XMLSchema-instance" xml:lang="de" xsi:schemaLocation="http://caaml.org/Schemas/V5.0/Profiles/BulletinEAWS http://caaml.org/Schemas/V5.0/Profiles/BulletinEAWS/CAAMLv5_BulletinEAWS.xsd">
  <metaDataProperty>
    <MetaData>
      <dateTimeReport>2025-04-21T15:00:00Z</dateTimeReport>
      <srcRef>
        <Operation>
          <name>Lawinen.report</name>
        </Operation>
      </srcRef>
    </MetaData>
  </metaDataProperty>
  <observations>
    <Bulletin gml:id="8fa73d45-14be-420f-948a-237fde0ba405" xml:lang="de">
      <metaDataProperty>
        <MetaData>
          <dateTimeReport>2025-04-21T15:00:00Z</dateTimeReport>
          <srcRef>
            <Operation>
              <name>Lawinen.report</name>
            </Operation>
          </srcRef>
        </MetaData>
      </metaDataProperty>
      <validTime>
        <TimePeriod>
          <beginPosition>2025-04-21T22:00:00Z</beginPosition>
          <endPosition>2025-04-22T22:00:00Z</endPosition>
        </TimePeriod>
      </validTime>
      <srcRef>
        <Operation>
          <name>Avalanche.report</name>
        </Operation>
      </srcRef>
      <locRef xlink:href="IT-34-BL-03"/>
      <locRef xlink:href="IT-34-BL-04"/>
      <locRef xlink:href="IT-34-BL-01"/>
      <locRef xlink:href="IT-34-BL-02"/>
      <bulletinResultsOf>
        <BulletinMeasurements>
          <dangerRatings>
            <DangerRating>
              <validElevation xlink:href="ElevationRange_2100Hi"/>
              <mainValue>2</mainValue>
            </DangerRating>
            <DangerRating>
              <validElevation xlink:href="ElevationRange_2100Lw"/>
              <mainValue>1</mainValue>
            </DangerRating>
          </dangerRatings>
          <avProblems>
            <AvProblem>
              <type>wet snow</type>
              <validAspect xlink:href="AspectRange_w"/>
              <validAspect xlink:href="AspectRange_ne"/>
              <validAspect xlink:href="AspectRange_s"/>
              <validAspect xlink:href="AspectRange_sw"/>
              <validAspect xlink:href="AspectRange_nw"/>
              <validAspect xlink:href="AspectRange_se"/>
              <validAspect xlink:href="AspectRange_n"/>
              <validAspect xlink:href="AspectRange_e"/>
              <validElevation xlink:href="ElevationRange_2100Lw"/>
            </AvProblem>
            <AvProblem>
              <type>wet snow</type>
              <validAspect xlink:href="AspectRange_w"/>
              <validAspect xlink:href="AspectRange_ne"/>
              <validAspect xlink:href="AspectRange_s"/>
              <validAspect xlink:href="AspectRange_sw"/>
              <validAspect xlink:href="AspectRange_nw"/>
              <validAspect xlink:href="AspectRange_se"/>
              <validAspect xlink:href="AspectRange_n"/>
              <validAspect xlink:href="AspectRange_e"/>
              <validElevation xlink:href="ElevationRange_2700Lw"/>
            </AvProblem>
            <AvProblem>
              <type>old snow</type>
              <validAspect xlink:href="AspectRange_w"/>
              <validAspect xlink:href="AspectRange_ne"/>
              <validAspect xlink:href="AspectRange_s"/>
              <validAspect xlink:href="AspectRange_sw"/>
              <validAspect xlink:href="AspectRange_nw"/>
              <validAspect xlink:href="AspectRange_se"/>
              <validAspect xlink:href="AspectRange_n"/>
              <validAspect xlink:href="AspectRange_e"/>
              <validElevation xlink:href="ElevationRange_2800Hi"/>
            </AvProblem>
          </avProblems>
          <tendency>
            <type>steady</type>
            <validTime>
              <TimePeriod>
                <beginPosition>2025-04-22T22:00:00Z</beginPosition>
                <endPosition>2025-04-23T22:00:00Z</endPosition>
              </TimePeriod>
            </validTime>
          </tendency>
          <avActivityHighlights>Die Gefahr von feuchten und nassen Lawinen steigt im Tagesverlauf etwas an. Vorsicht vor frischem Triebschnee. Die Lawinen können vereinzelt in tiefen Schichten anreißen.</avActivityHighlights>
          <avActivityComment>Die Aktivität von feuchten und nassen Lawinen nimmt mit der Erwärmung und der Sonneneinstrahlung nur langsam zu. Dies vor allem in Gipfellagen bei größeren Aufhellungen. Feuchte und nasse Lawinen können vereinzelt von einzelnen Wintersportlern ausgelöst werden. Lawinen können bis auf den Boden durchreißen. Die Triebschneeansammlungen müssen besonders an steilen Schattenhängen vorsichtig beurteilt werden. Neu- und Triebschnee müssen an allen Expositionen im Hochgebirge vorsichtig beurteilt werden.</avActivityComment>
          <snowpackStructureComment>Der Regen führte unterhalb von rund 2700 m zu einer zunehmenden Anfeuchtung der Schneedecke. Die Schneedecke wird allmählich feucht. Neu- und Triebschnee müssen an allen Expositionen im Hochgebirge vorsichtig beurteilt werden.</snowpackStructureComment>
        </BulletinMeasurements>
      </bulletinResultsOf>
    </Bulletin>
    <Bulletin gml:id="17e03810-2cdc-48dd-aae5-75f67b3d2754" xml:lang="de">
      <metaDataProperty>
        <MetaData>
          <dateTimeReport>2025-04-21T15:00:00Z</dateTimeReport>
          <srcRef>
            <Operation>
              <name>Lawinen.report</name>
            </Operation>
          </srcRef>
        </MetaData>
      </metaDataProperty>
      <validTime>
        <TimePeriod>
          <beginPosition>2025-04-21T22:00:00Z</beginPosition>
          <endPosition>2025-04-22T22:00:00Z</endPosition>
        </TimePeriod>
      </validTime>
      <srcRef>
        <Operation>
          <name>Avalanche.report</name>
        </Operation>
      </srcRef>
      <locRef xlink:href="IT-34-BL-05"/>
      <locRef xlink:href="IT-34-BL-06"/>
      <locRef xlink:href="IT-34-VR-01"/>
      <locRef xlink:href="IT-34-VI-01"/>
      <bulletinResultsOf>
        <BulletinMeasurements>
          <dangerRatings>
            <DangerRating>
              <mainValue>1</mainValue>
            </DangerRating>
          </dangerRatings>
          <avProblems>
            <AvProblem>
              <type>wet snow</type>
              <validAspect xlink:href="AspectRange_w"/>
              <validAspect xlink:href="AspectRange_ne"/>
              <validAspect xlink:href="AspectRange_s"/>
              <validAspect xlink:href="AspectRange_sw"/>
              <validAspect xlink:href="AspectRange_nw"/>
              <validAspect xlink:href="AspectRange_se"/>
              <validAspect xlink:href="AspectRange_n"/>
              <validAspect xlink:href="AspectRange_e"/>
            </AvProblem>
          </avProblems>
          <tendency>
            <type>steady</type>
            <validTime>
              <TimePeriod>
                <beginPosition>2025-04-22T22:00:00Z</beginPosition>
                <endPosition>2025-04-23T22:00:00Z</endPosition>
              </TimePeriod>
            </validTime>
          </tendency>
          <avActivityHighlights>Die spontane Lawinenaktivität nimmt mit der Erwärmung und der Sonneneinstrahlung zu.</avActivityHighlights>
          <avActivityComment>Nasse Lawinen können vereinzelt mit meist großer Belastung ausgelöst werden. Lawinen können sehr vereinzelt die durchnässte Schneedecke mitreißen und mittlere Größe erreichen. Mit der tageszeitlichen Erwärmung sind oberhalb von rund 1700 m kleine und mittlere feuchte und nasse Lawinen möglich.</avActivityComment>
          <snowpackStructureComment>Der Regen führte zu einer Anfeuchtung der Schneedecke.</snowpackStructureComment>
        </BulletinMeasurements>
      </bulletinResultsOf>
    </Bulletin>
  </observations>
</ObsCollection>
