<?xml version="1.0" encoding="UTF-8" standalone="yes" ?>
<?xml-stylesheet type="text/xsl" href="../web/bra.xslt"?>
<BULLETINS_NEIGE_AVALANCHE xmlns:xsi="http://www.w3.org/2001/XMLSchema-instance" xmlns:xsd="http://www.w3.org/2001/XMLSchema" TYPEBULLETIN="BRA" ID="66" MASSIF="Haute-Bigorre" DATEBULLETIN="2024-06-05T16:00:00" DATEECHEANCE="2024-06-06T18:00:00" DATEVALIDITE="2024-06-06T18:00:00" DATEDIFFUSION="2024-06-05T15:31:18" AMENDEMENT="false">
  <DateValidite>2024-06-06T18:00:00</DateValidite>
  <CARTOUCHERISQUE>
    <RISQUE RISQUE1="1" EVOLURISQUE1="" LOC1="" ALTITUDE="" RISQUE2="" EVOLURISQUE2="" LOC2="" RISQUEMAXI="1" COMMENTAIRE="Risque faible." RISQUEMAXIJ2="1" DATE_RISQUE_J2="2024-06-07T00:00:00"/>
    <PENTE NE="false" E="false" SE="false" S="false" SW="false" W="false" NW="false" N="false" COMMENTAIRE="Neige humide."/>
    <ACCIDENTEL><![CDATA[Difficiles, de surface en neige très humide.]]></ACCIDENTEL>
    <NATUREL><![CDATA[Rares départs ponctuels de surface ou de fond.]]></NATUREL>
    <RESUME><![CDATA[Départs spontanés : Rares départs ponctuels de surface ou de fond.
Déclenchements skieurs : Difficiles, de surface en neige très humide.]]></RESUME>
    <RisqueJ2><![CDATA[risque faible]]></RisqueJ2>
    <CommentaireRisqueJ2><![CDATA[Conditions similaires : manteau ressaisi en surface au petit matin, s'humidifiant rapidement. 
Rares avalanches de fond possibles.]]></CommentaireRisqueJ2>
    <AVIS/>
    <VIGILANCE/>
    <ImageRisque>montagne_risques_66.png</ImageRisque>
    <ImagePente>rose_pentes_66.png</ImagePente>
  </CARTOUCHERISQUE>
  <STABILITE>
    <SitAvalTyp SAT1="4" SAT2="5"/>
    <TEXTE><![CDATA[Manteau neigeux humidifié parfois en profondeur. Regel limité, au-dessus de 2600 m.

DEPARTS SPONTANES : Pas d'activité de surface à attendre au petit matin grâce à un léger regel ou saisissement, puis rares départs ponctuels de rares coulées en neige humide dans les pentes raides surtout en versant Nord à Est où il reste de la neige. Localement, principalement en secteur frontalier (Vignemale-Mont Perdu) plus enneigé, de rares avalanches de tailles moyennes sont possibles, par glissement complet du manteau neigeux très humide ou décrochement d'une corniche. L'aval et abords des fissures et ouvertures dans le manteau neigeux sont à éviter. 

DECLENCHEMENTS PROVOQUES : Neige ressaisie au petit matin, peu sensible aux sollicitations. Durant la journée, avec la douceur qui s'affirme, la neige molle en surface peut déstabiliser les pratiquants de la montagne. Des corniches restent sensibles à la rupture avec la douceur et une sollicitation. ]]></TEXTE>
  </STABILITE>
  <QUALITE>
    <TEXTE><![CDATA[Manteau neigeux et peu épais, excepté en secteurs frontaliers au-dessus de 2700 m où l'enneigement devient parfois important pour la saison.
Au petit matin, neige ressaisie, très légèrement regelée et croûtée au-dessus de 2700m, s'humidifiant rapidement en tous versants. Le phénomène de fonte devient prépondérant.
La vieille neige de sous-couche en Nord et Est est bien dense et portante, mais au-dessus de 2700 m en secteurs nord à est, la neige tombée en mai est gorgée d"'eau mais non tassée et l'enfoncement y est important.]]></TEXTE>
  </QUALITE>
  <ENNEIGEMENT DATE="2024-06-05T00:00:00" LimiteSud="2800" LimiteNord="2400">
    <NIVEAU ALTI="1500" N="0" S="0"/>
    <NIVEAU ALTI="2000" N="0" S="0"/>
    <NIVEAU ALTI="2500" N="42" S="0"/>
    <ImageEnneigement>montagne_enneigement_66.png</ImageEnneigement>
  </ENNEIGEMENT>
  <NEIGEFRAICHE ALTITUDESS="1800">
    <NEIGE24H DATE="2024-06-01T00:00:00" SS24Min="0" SS24Max="0"/>
    <NEIGE24H DATE="2024-06-02T00:00:00" SS24Min="0" SS24Max="0"/>
    <NEIGE24H DATE="2024-06-03T00:00:00" SS24Min="0" SS24Max="0"/>
    <NEIGE24H DATE="2024-06-04T00:00:00" SS24Min="0" SS24Max="0"/>
    <NEIGE24H DATE="2024-06-05T00:00:00" SS24Min="0" SS24Max="0"/>
    <NEIGE24H DATE="2024-06-06T00:00:00" SS24Min="0" SS24Max="0"/>
    <ImageNeigeFraiche>graphe_neige_fraiche_66.png</ImageNeigeFraiche>
  </NEIGEFRAICHE>
  <METEO ALTITUDEVENT1="2000" ALTITUDEVENT2="3000">
    <COMMENTAIRE>Ensoleillé le matin et cumulus entrelacés de ciel bleu en après-midi, vent de sud-ouest modéré à parfois assez fort.</COMMENTAIRE>
    <ECHEANCE DATE="2024-06-06T06:00:00" FF1="25" DD1="O" FF2="60" DD2="O" ISO0="4000" PLUIENEIGE="-1" TEMPSSENSIBLE="6" MERNUAGES="-1"/>
    <ECHEANCE DATE="2024-06-06T12:00:00" FF1="25" DD1="SO" FF2="60" DD2="SO" ISO0="4100" PLUIENEIGE="-1" TEMPSSENSIBLE="6" MERNUAGES="-1"/>
    <ECHEANCE DATE="2024-06-06T18:00:00" FF1="30" DD1="SO" FF2="60" DD2="SO" ISO0="4100" PLUIENEIGE="-1" TEMPSSENSIBLE="6" MERNUAGES="-1"/>
    <ECHEANCE DATE="2024-06-07T00:00:00" FF1="30" DD1="S" FF2="70" DD2="SO" ISO0="4100" PLUIENEIGE="3600" TEMPSSENSIBLE="90" MERNUAGES="-1"/>
    <ImageMeteo>apercu_meteo_66.png</ImageMeteo>
  </METEO>
  <BSH>
    <METEO>
      <ECHEANCE DATE="2024-05-30T06:00:00" FF1="15" DD1="O" FF2="60" DD2="NO" ISO0="4000" PLUIENEIGE="-1" TEMPSSENSIBLE="4"/>
      <ECHEANCE DATE="2024-05-30T12:00:00" FF1="15" DD1="N" FF2="60" DD2="NO" ISO0="3800" PLUIENEIGE="3500" TEMPSSENSIBLE="51"/>
      <ECHEANCE DATE="2024-05-30T18:00:00" FF1="15" DD1="NO" FF2="60" DD2="N" ISO0="3800" PLUIENEIGE="3500" TEMPSSENSIBLE="70"/>
      <ECHEANCE DATE="2024-05-31T00:00:00" FF1="25" DD1="NO" FF2="60" DD2="NO" ISO0="3600" PLUIENEIGE="-1" TEMPSSENSIBLE="7"/>
      <ECHEANCE DATE="2024-05-31T06:00:00" FF1="30" DD1="NO" FF2="60" DD2="NO" ISO0="3500" PLUIENEIGE="-1" TEMPSSENSIBLE="7"/>
      <ECHEANCE DATE="2024-05-31T12:00:00" FF1="10" DD1="N" FF2="50" DD2="NO" ISO0="3400" PLUIENEIGE="-1" TEMPSSENSIBLE="32"/>
      <ECHEANCE DATE="2024-05-31T18:00:00" FF1="5" DD1="O" FF2="40" DD2="O" ISO0="3000" PLUIENEIGE="-1" TEMPSSENSIBLE="4"/>
      <ECHEANCE DATE="2024-06-01T00:00:00" FF1="0" DD1="SE" FF2="35" DD2="NO" ISO0="2400" PLUIENEIGE="2200" TEMPSSENSIBLE="71"/>
      <ECHEANCE DATE="2024-06-01T06:00:00" FF1="5" DD1="E" FF2="30" DD2="N" ISO0="2300" PLUIENEIGE="-1" TEMPSSENSIBLE="3"/>
      <ECHEANCE DATE="2024-06-01T12:00:00" FF1="5" DD1="N" FF2="20" DD2="N" ISO0="2400" PLUIENEIGE="-1" TEMPSSENSIBLE="3"/>
      <ECHEANCE DATE="2024-06-01T18:00:00" FF1="10" DD1="N" FF2="20" DD2="N" ISO0="2500" PLUIENEIGE="2300" TEMPSSENSIBLE="70"/>
      <ECHEANCE DATE="2024-06-02T00:00:00" FF1="5" DD1="Vrb" FF2="20" DD2="N" ISO0="2500" PLUIENEIGE="2300" TEMPSSENSIBLE="71"/>
      <ECHEANCE DATE="2024-06-02T06:00:00" FF1="5" DD1="N" FF2="20" DD2="N" ISO0="2600" PLUIENEIGE="2400" TEMPSSENSIBLE="71"/>
      <ECHEANCE DATE="2024-06-02T12:00:00" FF1="5" DD1="N" FF2="20" DD2="N" ISO0="3000" PLUIENEIGE="-1" TEMPSSENSIBLE="2"/>
      <ECHEANCE DATE="2024-06-02T18:00:00" FF1="5" DD1="N" FF2="20" DD2="SO" ISO0="3400" PLUIENEIGE="3200" TEMPSSENSIBLE="71"/>
      <ECHEANCE DATE="2024-06-03T00:00:00" FF1="5" DD1="Vrb" FF2="10" DD2="O" ISO0="3400" PLUIENEIGE="-1" TEMPSSENSIBLE="7"/>
      <ECHEANCE DATE="2024-06-03T06:00:00" FF1="5" DD1="Vrb" FF2="10" DD2="N" ISO0="3600" PLUIENEIGE="-1" TEMPSSENSIBLE="2"/>
      <ECHEANCE DATE="2024-06-03T12:00:00" FF1="5" DD1="Vrb" FF2="10" DD2="SO" ISO0="3400" PLUIENEIGE="-1" TEMPSSENSIBLE="3"/>
      <ECHEANCE DATE="2024-06-03T18:00:00" FF1="10" DD1="NO" FF2="20" DD2="SO" ISO0="3600" PLUIENEIGE="3400" TEMPSSENSIBLE="70"/>
      <ECHEANCE DATE="2024-06-04T00:00:00" FF1="10" DD1="NO" FF2="30" DD2="O" ISO0="3600" PLUIENEIGE="-1" TEMPSSENSIBLE="2"/>
      <ECHEANCE DATE="2024-06-04T06:00:00" FF1="15" DD1="S" FF2="30" DD2="SO" ISO0="3300" PLUIENEIGE="-1" TEMPSSENSIBLE="32"/>
      <ECHEANCE DATE="2024-06-04T12:00:00" FF1="20" DD1="O" FF2="30" DD2="O" ISO0="3400" PLUIENEIGE="-1" TEMPSSENSIBLE="2"/>
      <ECHEANCE DATE="2024-06-04T18:00:00" FF1="15" DD1="NO" FF2="35" DD2="SO" ISO0="3600" PLUIENEIGE="-1" TEMPSSENSIBLE="71"/>
      <ECHEANCE DATE="2024-06-05T00:00:00" FF1="15" DD1="O" FF2="60" DD2="O" ISO0="3700" PLUIENEIGE="-1" TEMPSSENSIBLE="2"/>
      <ECHEANCE DATE="2024-06-05T06:00:00" FF1="15" DD1="SO" FF2="80" DD2="O" ISO0="3900" PLUIENEIGE="-1" TEMPSSENSIBLE="4"/>
      <ECHEANCE DATE="2024-06-05T12:00:00" FF1="25" DD1="O" FF2="70" DD2="O" ISO0="4000" PLUIENEIGE="-1" TEMPSSENSIBLE="2"/>
      <ECHEANCE DATE="2024-06-05T18:00:00" FF1="15" DD1="O" FF2="55" DD2="SO" ISO0="4000" PLUIENEIGE="-1" TEMPSSENSIBLE="4"/>
      <ECHEANCE DATE="2024-06-06T00:00:00" FF1="15" DD1="SO" FF2="55" DD2="O" ISO0="3900" PLUIENEIGE="-1" TEMPSSENSIBLE="6"/>
    </METEO>
    <ENNEIGEMENTS>
      <ENNEIGEMENT DATE="2024-05-30T00:00:00" LimiteSud="2700" LimiteNord="2300">
        <NIVEAU ALTI="1500" N="0" S="0"/>
        <NIVEAU ALTI="2000" N="0" S="0"/>
        <NIVEAU ALTI="2500" N="65" S="0"/>
      </ENNEIGEMENT>
      <ENNEIGEMENT DATE="2024-05-31T00:00:00" LimiteSud="2700" LimiteNord="2300">
        <NIVEAU ALTI="1500" N="0" S="0"/>
        <NIVEAU ALTI="2000" N="0" S="0"/>
        <NIVEAU ALTI="2500" N="65" S="0"/>
      </ENNEIGEMENT>
      <ENNEIGEMENT DATE="2024-06-01T00:00:00" LimiteSud="2700" LimiteNord="2300">
        <NIVEAU ALTI="1500" N="0" S="0"/>
        <NIVEAU ALTI="2000" N="0" S="0"/>
        <NIVEAU ALTI="2500" N="60" S="0"/>
      </ENNEIGEMENT>
      <ENNEIGEMENT DATE="2024-06-02T06:00:00" LimiteSud="2700" LimiteNord="2300">
        <NIVEAU ALTI="1500" N="0" S="0"/>
        <NIVEAU ALTI="2000" N="0" S="0"/>
        <NIVEAU ALTI="2500" N="55" S="0"/>
      </ENNEIGEMENT>
      <ENNEIGEMENT DATE="2024-06-03T00:00:00" LimiteSud="2700" LimiteNord="2300">
        <NIVEAU ALTI="1500" N="0" S="0"/>
        <NIVEAU ALTI="2000" N="0" S="0"/>
        <NIVEAU ALTI="2500" N="50" S="0"/>
      </ENNEIGEMENT>
      <ENNEIGEMENT DATE="2024-06-04T00:00:00" LimiteSud="2800" LimiteNord="2300">
        <NIVEAU ALTI="1500" N="0" S="0"/>
        <NIVEAU ALTI="2000" N="0" S="0"/>
        <NIVEAU ALTI="2500" N="50" S="0"/>
      </ENNEIGEMENT>
      <ENNEIGEMENT DATE="2024-06-05T00:00:00" LimiteSud="2800" LimiteNord="2400">
        <NIVEAU ALTI="1500" N="0" S="0"/>
        <NIVEAU ALTI="2000" N="0" S="0"/>
        <NIVEAU ALTI="2500" N="42" S="0"/>
      </ENNEIGEMENT>
    </ENNEIGEMENTS>
    <NEIGEFRAICHE ALTITUDESS="1800">
      <NEIGE24H DATE="2024-05-31T00:00:00" SS24Min="0" SS24Max="0"/>
      <NEIGE24H DATE="2024-06-01T00:00:00" SS24Min="0" SS24Max="0"/>
      <NEIGE24H DATE="2024-06-02T06:00:00" SS24Min="0" SS24Max="0"/>
      <NEIGE24H DATE="2024-06-03T00:00:00" SS24Min="0" SS24Max="0"/>
      <NEIGE24H DATE="2024-06-04T00:00:00" SS24Min="0" SS24Max="0"/>
      <NEIGE24H DATE="2024-06-05T00:00:00" SS24Min="0" SS24Max="0"/>
    </NEIGEFRAICHE>
    <RISQUES>
      <RISQUE DATE="2024-05-30T00:00:00" RISQUEMAXI="2"/>
      <RISQUE DATE="2024-05-31T00:00:00" RISQUEMAXI="2"/>
      <RISQUE DATE="2024-06-01T00:00:00" RISQUEMAXI="2"/>
      <RISQUE DATE="2024-06-02T00:00:00" RISQUEMAXI="2"/>
      <RISQUE DATE="2024-06-03T00:00:00" RISQUEMAXI="2"/>
      <RISQUE DATE="2024-06-04T00:00:00" RISQUEMAXI="2"/>
      <RISQUE DATE="2024-06-05T00:00:00" RISQUEMAXI="2"/>
    </RISQUES>
    <Image7derniersjours>sept_derniers_jours_66.png</Image7derniersjours>
    <Image7derniersjours_portrait>sept_derniers_jours_portrait_66.png</Image7derniersjours_portrait>
  </BSH>
  <TexteMeta>
    <Vigilance>Pour consulter la vigilance en cours, veuillez vous rendre sur le site <a href="https://vigilance.meteofrance.fr/fr">https://vigilance.meteofrance.fr/fr</a></Vigilance>
    <EnteteGenerique/>
    <BasDePageGenerique/>
    <LienDocumentation/>
    <Partenaires>Rédigé par Météo-France avec la contribution des observateurs du réseau nivo-météorologique. Partenariat : ANMSM (Maires de Stations de Montagne), DSF (Domaines Skiables de France), ADSP (Directeurs de Pistes et de la Sécurité des Stations de Sports d'Hiver) et autres acteurs de la montagne.</Partenaires>
  </TexteMeta>
</BULLETINS_NEIGE_AVALANCHE>