{
  "bulletins" : [ {
    "publicationTime" : "2026-01-03T06:45:32Z",
    "validTime" : {
      "startTime" : "2026-01-02T16:00:00Z",
      "endTime" : "2026-01-03T16:00:00Z"
    },
    "unscheduled" : true,
    "source" : {
      "person" : {
        "name" : "Avalanche Service Bavaria"
      }
    },
    "avalancheActivity" : {
      "highlights" : "Fresh and older wind slabs are prone to triggering.",
      "comment" : "The avalanche danger is moderate above 2000 metres and low below that. In some places, wind slab avalanches can be triggered as small to medium sized slab avalanches at high altitudes due to low additional loads. This occurs adjacent to the ridgeline and distant from ridgelines in steep terrain in northern and eastern aspects as well as in gullies and bowls. In addition to the risk of burial, the risk of being swept away and falling must be taken into account."
    },
    "snowpackStructure" : {
      "comment" : "Fresh and older snowdrift accumulations lie on unfavourable layers, especially on the shady slopes, sometimes prone to triggering. At higher and higher altitudes, faceted crystals are often found below a melt-freeze crust close to the surface. Snow depths are below average at all altitudes."
    },
    "tendency" : [ {
      "highlights" : "Slow decline in avalanche danger.",
      "validTime" : {
        "startTime" : "2026-01-03T16:00:00Z",
        "endTime" : "2026-01-04T16:00:00Z"
      }
    } ],
    "customData" : {
      "ALBINA" : {
        "mainDate" : "2026-01-03"
      },
      "LWD_Tyrol" : {
        "dangerPatterns" : [ ]
      }
    },
    "avalancheProblems" : [ {
      "problemType" : "wind_slab",
      "elevation" : {
        "lowerBound" : "2000"
      },
      "validTimePeriod" : "all_day",
      "customData" : {
        "ALBINA" : {
          "avalancheType" : "slab"
        }
      },
      "aspects" : [ "NW", "N", "SE", "E", "NE" ]
    } ],
    "bulletinID" : "c88f6ca2-58e1-4641-a229-87c073d99b50",
    "dangerRatings" : [ {
      "mainValue" : "low",
      "elevation" : {
        "upperBound" : "2000"
      },
      "validTimePeriod" : "all_day"
    }, {
      "mainValue" : "moderate",
      "elevation" : {
        "lowerBound" : "2000"
      },
      "validTimePeriod" : "all_day"
    } ],
    "lang" : "en",
    "regions" : [ {
      "name" : "Berchtesgaden Alps",
      "regionID" : "DE-BY-60"
    } ]
  }, {
    "publicationTime" : "2026-01-03T06:45:32Z",
    "validTime" : {
      "startTime" : "2026-01-02T16:00:00Z",
      "endTime" : "2026-01-03T16:00:00Z"
    },
    "unscheduled" : true,
    "source" : {
      "person" : {
        "name" : "Avalanche Service Bavaria"
      }
    },
    "avalancheActivity" : {
      "highlights" : "Avalanches can be of medium size.",
      "comment" : "The avalanche risk is moderate above the tree line and low below. Wind slab avalanches can be triggered by even a small additional load. This occurs adjacent to the ridgeline and distant from ridgelines in steep terrain in northern and eastern aspects as well as in gullies and bowls. Avalanches can reach medium size. In addition to the risk of burial, the risk of being swept away and falling must be taken into account."
    },
    "snowpackStructure" : {
      "comment" : "With a focus on the Allgäu, 10-25 centimetres of new fallen snow will fall, carried by stormy winds from westerly directions. The fresh and older snowdrift accumulations often lie unfavourably on a thin melt-freeze crust, especially on the shady slopes. Under the melt-freeze crust, the snow has built up and forms a weak layer. Intermediate layers prone to triggering can also be contained within the wind slab. The snow depths are below average at all altitudes."
    },
    "tendency" : [ {
      "highlights" : "Slow decline in avalanche danger.",
      "validTime" : {
        "startTime" : "2026-01-03T16:00:00Z",
        "endTime" : "2026-01-04T16:00:00Z"
      }
    } ],
    "customData" : {
      "ALBINA" : {
        "mainDate" : "2026-01-03"
      },
      "LWD_Tyrol" : {
        "dangerPatterns" : [ ]
      }
    },
    "avalancheProblems" : [ {
      "problemType" : "wind_slab",
      "elevation" : {
        "lowerBound" : "treeline"
      },
      "validTimePeriod" : "all_day",
      "customData" : {
        "ALBINA" : {
          "avalancheType" : "slab"
        }
      },
      "aspects" : [ "NW", "N", "SE", "E", "NE" ]
    } ],
    "bulletinID" : "5da3b74b-4d1f-4d73-b2f9-46afde81328f",
    "dangerRatings" : [ {
      "mainValue" : "low",
      "elevation" : {
        "upperBound" : "treeline"
      },
      "validTimePeriod" : "all_day"
    }, {
      "mainValue" : "moderate",
      "elevation" : {
        "lowerBound" : "treeline"
      },
      "validTimePeriod" : "all_day"
    } ],
    "lang" : "en",
    "regions" : [ {
      "name" : "Werdenfels Alps",
      "regionID" : "DE-BY-30"
    }, {
      "name" : "Bavarian Prealps West",
      "regionID" : "DE-BY-41"
    }, {
      "name" : "Allgäu  Alps Central",
      "regionID" : "DE-BY-12"
    }, {
      "name" : "Allgäu  Prealps",
      "regionID" : "DE-BY-11"
    }, {
      "name" : "Bavarian Prealps East",
      "regionID" : "DE-BY-43"
    }, {
      "name" : "Bavarian Prealps Central",
      "regionID" : "DE-BY-42"
    }, {
      "name" : "Ammergau Alps North",
      "regionID" : "DE-BY-20"
    } ]
  }, {
    "publicationTime" : "2026-01-03T06:45:32Z",
    "validTime" : {
      "startTime" : "2026-01-02T16:00:00Z",
      "endTime" : "2026-01-03T16:00:00Z"
    },
    "unscheduled" : true,
    "source" : {
      "person" : {
        "name" : "Avalanche Service Bavaria"
      }
    },
    "avalancheActivity" : {
      "highlights" : "Watch out for small snowdrift accumulations.",
      "comment" : "The avalanche risk is low.  Occasionally, small snowdrift accumulations can be triggered as a small slab by a small additional load. This occurs adjacent to the ridgeline and distant from ridgelines in the steep terrain of northern and eastern aspects. Be aware of the risk of being swept away and falling."
    },
    "snowpackStructure" : {
      "comment" : "Stormy winds and a few centimetres of new fallen snow have created small-scale wind slabs. The fresh and older snowdrift accumulations are only slightly thick, but are prone to triggering, especially on the shady slopes. At higher and higher altitudes, there are often faceted crystals down to the ground below a melt-freeze crust close to the surface. There are only a few centimetres of snow on the sunny slopes."
    },
    "tendency" : [ {
      "highlights" : "Little change.",
      "validTime" : {
        "startTime" : "2026-01-03T16:00:00Z",
        "endTime" : "2026-01-04T16:00:00Z"
      }
    } ],
    "customData" : {
      "ALBINA" : {
        "mainDate" : "2026-01-03"
      },
      "LWD_Tyrol" : {
        "dangerPatterns" : [ ]
      }
    },
    "avalancheProblems" : [ {
      "problemType" : "wind_slab",
      "elevation" : { },
      "validTimePeriod" : "all_day",
      "customData" : {
        "ALBINA" : {
          "avalancheType" : "slab"
        }
      },
      "aspects" : [ "NW", "N", "SE", "E", "NE" ]
    } ],
    "bulletinID" : "79178c0f-f124-4fa3-9ca3-eeeaf2ee3332",
    "dangerRatings" : [ {
      "mainValue" : "low",
      "validTimePeriod" : "all_day"
    } ],
    "lang" : "en",
    "regions" : [ {
      "name" : "Chiemgau Alps East",
      "regionID" : "DE-BY-52"
    }, {
      "name" : "Chiemgau Alps West",
      "regionID" : "DE-BY-51"
    } ]
  } ],
  "customData" : {
    "ALBINA" : {
      "generalHeadline" : "Update: More new fallen snow than expected in the Bavarian Prealps."
    }
  }
}